{
  "sequences": [
    {
      "index": [
        1,
        0
      ],
      "loop": true,
      "steps": [
        {
          "scenes": [
            [
              0,
              0
            ],
            [
              1,
              0
            ]
          ],
          "duration": 3.5,
          "name": "Step 1",
          "duration_unit": "bars"
        },
        {
          "scenes": [
            [
              0,
              1
            ],
            [
              1,
              1
            ]
          ],
          "duration": 0.5,
          "name": "Step 2",
          "duration_unit": "bars"
        }
      ]
    }
  ]
}